mkdocs_markdown_filter/__init__.py
mkdocs_markdown_filter/plugin.py
mkdocs_markdown_filter-0.1.1.dist-info/LICENSE
mkdocs_markdown_filter-0.1.1.dist-info/METADATA
mkdocs_markdown_filter-0.1.1.dist-info/WHEEL
mkdocs_markdown_filter-0.1.1.dist-info/entry_points.txt
mkdocs_markdown_filter-0.1.1.dist-info/top_level.txt
mkdocs_markdown_filter-0.1.1.dist-info/RECORD
