Metadata-Version: 2.1
Name: mkdocs-markdown-filter
Version: 0.1.1
Summary: A MkDocs plugin to add a markdown filter to jinja templates.
Home-page: https://github.com/byrnereese/mkdocs-markdown-filter
Author: Byrne Reese
Author-email: byrne@majordojo.com
License: MIT
Keywords: mkdocs jinja
Platform: UNKNOWN
Classifier: Development Status :: 4 - Beta
Classifier: Intended Audience :: Developers
Classifier: Intended Audience :: Information Technology
Classifier: License :: OSI Approved :: MIT License
Classifier: Programming Language :: Python
Classifier: Programming Language :: Python :: 3 :: Only
Classifier: Programming Language :: Python :: 3.4
Classifier: Programming Language :: Python :: 3.5
Classifier: Programming Language :: Python :: 3.6
Classifier: Programming Language :: Python :: 3.7
Requires-Python: >=2.7
Requires-Dist: mkdocs (>=1.0.4)
